hstgrism/__init__.py
hstgrism/background.py
hstgrism/computesip.py
hstgrism/computetracenwavelength.py
hstgrism/computexyref.py
hstgrism/confreader.py
hstgrism/container.py
hstgrism/contamination.py
hstgrism/cutout2d.py
hstgrism/extract.py
hstgrism/flatfield.py
hstgrism/grismapcorr.py
hstgrism/headersummary.py
hstgrism/objectmask.py
hstgrism/show_bbox.py
hstgrism/show_overview.py
hstgrism/show_sum1d.py
hstgrism/sub2full.py
hstgrism/to_fullframe.py
hstgrism/wfc3irg102.py
hstgrism/wfc3irg141.py
hstgrism/wfc3uvisg280.py
hstgrism-8.5.0.dist-info/LICENSE
hstgrism-8.5.0.dist-info/METADATA
hstgrism-8.5.0.dist-info/WHEEL
hstgrism-8.5.0.dist-info/top_level.txt
hstgrism-8.5.0.dist-info/RECORD
