Metadata-Version: 2.1
Name: hstgrism
Version: 8.5.0
Summary: UNKNOWN
Home-page: https://github.com/bkornpob/hstgrism
Author: Kornpob Bhirombhakdi
Author-email: kbhirombhakdi@stsci.edu
License: UNKNOWN
Platform: UNKNOWN
Classifier: Programming Language :: Python :: 3
Classifier: License :: OSI Approved :: MIT License
Classifier: Operating System :: OS Independent
Requires-Python: >=3.
